shazam_to_youtube/main.py
shazam_to_youtube/yt_auth.py
shazam_to_youtube-0.1.3.dist-info/METADATA
shazam_to_youtube-0.1.3.dist-info/WHEEL
shazam_to_youtube-0.1.3.dist-info/entry_points.txt
shazam_to_youtube-0.1.3.dist-info/RECORD
