Metadata-Version: 2.1
Name: shazam-to-youtube
Version: 0.1.3
Summary: Create a Youtube Playlist from Shazam hits
License: MIT
Author: Torstein Sørnes
Author-email: t.soernes@gmail.com
Requires-Python: >=3.11,<4.0
Classifier: License :: OSI Approved :: MIT License
Classifier: Programming Language :: Python :: 3
Classifier: Programming Language :: Python :: 3.11
Classifier: Programming Language :: Python :: 3.12
Requires-Dist: pandas (>=2.2.3,<3.0.0)
Requires-Dist: spotify2ytmusic (>=0.9.30,<0.10.0)
